main.py
setup.py
offline_RL_congestion_control.egg-info/PKG-INFO
offline_RL_congestion_control.egg-info/SOURCES.txt
offline_RL_congestion_control.egg-info/dependency_links.txt
offline_RL_congestion_control.egg-info/requires.txt
offline_RL_congestion_control.egg-info/top_level.txt